README.md
setup.py
streamdal_protos/__init__.py
streamdal_protos.egg-info/PKG-INFO
streamdal_protos.egg-info/SOURCES.txt
streamdal_protos.egg-info/dependency_links.txt
streamdal_protos.egg-info/top_level.txt
streamdal_protos/protos/__init__.py
streamdal_protos/protos/shared/__init__.py
streamdal_protos/protos/steps/__init__.py