Metadata-Version: 2.1
Name: streamdal-protos
Version: 0.1.22
Summary: Protobuf python package for Streamdal.com server and SDKs
Home-page: https://github.com/streamdal/streamdal/tree/main/libs/protos
Author: Streamdal.com
Author-email: engineering@streamdal.com
License: MIT
Platform: UNKNOWN
Classifier: Development Status :: 1 - Planning
Classifier: License :: OSI Approved :: MIT License
Classifier: Programming Language :: Python :: 3.7
Classifier: Programming Language :: Python :: 3.8
Classifier: Programming Language :: Python :: 3.9
Classifier: Programming Language :: Python :: 3.10
Classifier: Programming Language :: Python :: 3.11
Requires-Python: >=3.7
